Metadata-Version: 2.1
Name: labelmap
Version: 0.0.1
Summary: Generate label maps from CSV files
Home-page: https://github.com/nzx9/LabelMap
Author: Navindu Dananga
Author-email: navindum@protonmail.com
License: MIT
Platform: UNKNOWN
Classifier: Programming Language :: Python :: 3
Classifier: License :: OSI Approved :: MIT License
Classifier: Operating System :: OS Independent
Requires-Python: >=3.6
License-File: LICENSE
